dji_metadata_embedder/__init__.py
dji_metadata_embedder/__main__.py
dji_metadata_embedder/cli.py
dji_metadata_embedder/dat_parser.py
dji_metadata_embedder/embedder.py
dji_metadata_embedder/metadata_check.py
dji_metadata_embedder/per_frame_embedder.py
dji_metadata_embedder/telemetry_converter.py
dji_metadata_embedder/utilities.py
dji_metadata_embedder/core/__init__.py
dji_metadata_embedder/core/processor.py
dji_metadata_embedder/core/validator.py
dji_metadata_embedder/utils/__init__.py
dji_metadata_embedder/utils/dependency_manager.py
dji_metadata_embedder/utils/system_info.py
dji_drone_metadata_embedder-1.1.2.dist-info/METADATA
dji_drone_metadata_embedder-1.1.2.dist-info/WHEEL
dji_drone_metadata_embedder-1.1.2.dist-info/entry_points.txt
dji_drone_metadata_embedder-1.1.2.dist-info/licenses/LICENSE
dji_drone_metadata_embedder-1.1.2.dist-info/RECORD
