Metadata-Version: 2.4
Name: dji-drone-metadata-embedder
Version: 1.1.2
Summary: Python CLI for embedding DJI drone telemetry from SRT logs into MP4 videos
Project-URL: Homepage, https://github.com/CallMarcus/dji-drone-metadata-embedder
Project-URL: Issues, https://github.com/CallMarcus/dji-drone-metadata-embedder/issues
Project-URL: Repository, https://github.com/CallMarcus/dji-drone-metadata-embedder.git
Author-email: "Marcus W." <marcus.westermark@altal.fi>
License: MIT License
License-File: LICENSE
Keywords: dji,drone,gps,metadata,srt,telemetry,video
Classifier: Development Status :: 4 - Beta
Classifier: Intended Audience :: End Users/Desktop
Classifier: License :: OSI Approved :: MIT License
Classifier: Programming Language :: Python :: 3
Classifier: Programming Language :: Python :: 3.10
Classifier: Programming Language :: Python :: 3.11
Classifier: Programming Language :: Python :: 3.12
Classifier: Topic :: Multimedia :: Video
Classifier: Topic :: Scientific/Engineering :: GIS
Requires-Python: >=3.10
Requires-Dist: click>=8.0.0
Requires-Dist: rich>=10.0.0
Provides-Extra: dev
Requires-Dist: black; extra == 'dev'
Requires-Dist: mypy; extra == 'dev'
Requires-Dist: pytest>=6.0; extra == 'dev'
Requires-Dist: ruff; extra == 'dev'
